{
  "cards": [
    {
      "name": "热播影视",
      "cards": [
        {
          "name": "好事成双",
          "img": "https://yc.cdn.media.ulivetv.net/media/img/2023-09-19/429d1e24001db9788af70c596089e0da.webp",
          "id": 98573,
          "countStr": "",
          "url": ""
        },
        {
          "name": "兰闺喜事",
          "img": "https://yc.cdn.media.ulivetv.net/media/img/2023-09-22/f0320e366635529e9ce2bc53059ddb15.webp",
          "id": 98636,
          "countStr": "",
          "url": ""
        },
        {
          "name": "爱回家之开心速递",
          "img": "https://yc.cdn.media.ulivetv.net/media/img/2023-05-18/df1f6e4e529cce43f8be5eb23f8fd341.webp",
          "id": 36506,
          "countStr": "",
          "url": "",
          "key": "闪电资源"
        },
        {
          "name": "特工任务",
          "img": "https://yc.cdn.media.ulivetv.net/media/img/2023-09-21/bc45a2341eaea58e35e27091d5103dcc.webp",
          "id": 98593,
          "countStr": "共38集",
          "url": ""
        },
        {
          "name": "你好，我的大夫（粤）",
          "img": "https://yc.cdn.media.ulivetv.net/media/img/2023-09-12/f03214cbce26736c7759738e8b5a6326.webp",
          "id": 98327,
          "countStr": "",
          "url": ""
        },
        {
          "name": "异人之下",
          "img": "https://yc.cdn.media.ulivetv.net/media/img/2023-08-04/3d614dafcfa1cc9894cb3085182560cb.webp",
          "id": 97613,
          "countStr": "",
          "url": ""
        },
        {
          "name": "西出玉门",
          "img": "https://yc.cdn.media.ulivetv.net/media/img/2023-05-18/1bc7d4db4e49c03836264e0b161fd8e7.webp",
          "id": 98245,
          "countStr": "",
          "url": ""
        },
        {
          "name": "虎鹤妖师录",
          "img": "https://yc.cdn.media.ulivetv.net/media/img/2023-10-02/d3c083b5dfacb2335d3b0e8d53be3cc5.jpg",
          "id": 98983,
          "countStr": "",
          "url": ""
        },
        {
          "name": "流光之下",
          "img": "https://yc.cdn.media.ulivetv.net/media/img/2023-09-20/d1af9211f48e4e9422def411f9f9feb7.webp",
          "id": 98603,
          "countStr": "",
          "url": ""
        },
        {
          "name": "披荆斩棘第三季",
          "img": "https://yc.cdn.media.ulivetv.net/media/img/2023-08-19/bac6e62b754b4ad49bf071066dc120d0.webp",
          "id": 97857,
          "countStr": "",
          "url": ""
        },
        {
          "name": "有生之年",
          "img": "https://yc.cdn.media.ulivetv.net/media/img/2023-09-17/f9d359b847236ebd01f0e3bb62a92452.webp",
          "id": 98515,
          "countStr": "",
          "url": ""
        },
        {
          "name": "南风知我意",
          "img": "https://yc.cdn.media.ulivetv.net/media/img/2023-09-12/e8f382be7db601fd6fb32a6151a5af6d.webp",
          "id": 98339,
          "countStr": "",
          "url": ""
        },
        {
          "name": "他从火光中走来",
          "img": "https://yc.cdn.media.ulivetv.net/media/img/2023-09-19/6eeadfb1c0daa47d9bdba47c6412e350.webp",
          "id": 98571,
          "countStr": "",
          "url": ""
        },
        {
          "name": "问心",
          "img": "https://yc.cdn.media.ulivetv.net/media/img/2023-10-07/0f6e5a2978097ff6faaa88faf5bca99f.jpg",
          "id": 99192,
          "countStr": "",
          "url": ""
        },
        {
          "name": "伸冤人3",
          "img": "https://yc.cdn.media.ulivetv.net/media/img/2023-10-03/38175da0c138c64a6126f4e5c33945c0.jpg",
          "id": 98194,
          "countStr": "",
          "url": ""
        },
        {
          "name": "花溪记",
          "img": "https://yc.cdn.media.ulivetv.net/media/img/2023-05-18/3139c39f6922260d2d3bb79d8f97bf6b.webp",
          "id": 98488,
          "countStr": "",
          "url": ""
        }
      ]
    },
    {
      "name": "电影",
      "cards": [
        {
          "name": "亚特兰蒂斯的阴谋",
          "img": "https://pic1.yzzyimg.com/upload/vod/2022-05-08/202205081651987021.jpg",
          "id": 187708,
          "countStr": "",
          "url": "https://cdn3.yzzy-online.com/20220507/17513_cbba2a6c/index.m3u8"
        },
        {
          "name": "打金枝",
          "img": "https://pic1.yzzyimg.com/upload/vod/2022-07-11/16575150861.jpg",
          "id": 185921,
          "countStr": "",
          "url": "https://cdn7.yzzy-online.com/20220711/4425_13e39831/index.m3u8"
        },
        {
          "name": "都是狗狗惹的祸",
          "img": "https://pic1.yzzyimg.com/upload/vod/2022-05-08/165198520117.jpg",
          "id": 187650,
          "countStr": "",
          "url": "https://cdn3.yzzy-online.com/20220508/17854_6764743a/index.m3u8"
        },
        {
          "name": "永贻芬芳",
          "img": "https://pic1.yzzyimg.com/upload/vod/2022-05-08/16520161341.jpg",
          "id": 187591,
          "countStr": "",
          "url": "https://cdn3.yzzy-online.com/20220509/18176_fdfa957e/index.m3u8"
        },
        {
          "name": "展旦召",
          "img": "https://pic1.yzzyimg.com/upload/vod/2022-05-08/16520164201.jpg",
          "id": 187593,
          "countStr": "",
          "url": "https://cdn3.yzzy-online.com/20220509/18178_a9cbdb06/index.m3u8"
        },
        {
          "name": "花园农家",
          "img": "https://pic1.yzzyimg.com/upload/vod/2022-05-09/16520892851.jpg",
          "id": 187586,
          "countStr": "",
          "url": "https://cdn3.yzzy-online.com/20220509/18254_b24f0b72/index.m3u8"
        },
        {
          "name": "走出大墙的人",
          "img": "https://pic1.yzzyimg.com/upload/vod/2022-05-09/16520595311.jpg",
          "id": 187584,
          "countStr": "",
          "url": "https://cdn3.yzzy-online.com/20220509/18230_e3b259a6/index.m3u8"
        },
        {
          "name": "茶恋",
          "img": "https://pic1.yzzyimg.com/upload/vod/2022-05-08/16520118991.jpg",
          "id": 187597,
          "countStr": "",
          "url": "https://cdn3.yzzy-online.com/20220509/18119_5bb10f94/index.m3u8"
        },
        {
          "name": "背上歌声去远方",
          "img": "https://pic1.yzzyimg.com/upload/vod/2022-06-05/16544358561.jpg",
          "id": 186819,
          "countStr": "",
          "url": "https://cdn4.yzzy-online.com/20220606/17294_d651865a/index.m3u8"
        },
        {
          "name": "点亮欧洲",
          "img": "https://pic1.yzzyimg.com/upload/vod/2022-05-08/16520126211.jpg",
          "id": 187598,
          "countStr": "",
          "url": "https://cdn3.yzzy-online.com/20220509/18123_3a50c4b4/index.m3u8"
        },
        {
          "name": "情义两重天",
          "img": "https://pic1.yzzyimg.com/upload/vod/2022-06-05/16544268031.jpg",
          "id": 186818,
          "countStr": "",
          "url": "https://cdn4.yzzy-online.com/20220605/17175_ad8851bd/index.m3u8"
        },
        {
          "name": "竹叶青传奇",
          "img": "https://pic1.yzzyimg.com/upload/vod/2022-05-12/16523638721.jpg",
          "id": 187400,
          "countStr": "",
          "url": "https://cdn3.yzzy-online.com/20220512/20972_1061f7e0/index.m3u8"
        },
        {
          "name": "阿K诗篇",
          "img": "https://pic1.yzzyimg.com/upload/vod/2022-05-08/16520136081.jpg",
          "id": 187611,
          "countStr": "",
          "url": "https://cdn3.yzzy-online.com/20220509/18111_ef27be78/index.m3u8"
        },
        {
          "name": "嘘声",
          "img": "https://pic1.yzzyimg.com/upload/vod/2022-05-07/165189775516.jpg",
          "id": 187703,
          "countStr": "",
          "url": "https://cdn3.yzzy-online.com/20220507/17510_d37d0507/index.m3u8"
        },
        {
          "name": "热恋中的女人",
          "img": "https://pic1.yzzyimg.com/upload/vod/2022-06-16/16553534031.jpg",
          "id": 186448,
          "countStr": "",
          "url": "https://cdn4.yzzy-online.com/20220616/21023_6acf6376/index.m3u8"
        },
        {
          "name": "踏尽江湖路国语版",
          "img": "https://pic1.yzzyimg.com/upload/vod/2022-05-10/16521467771.jpg",
          "id": 187564,
          "countStr": "",
          "url": "https://cdn4.yzzy-online.com/20220503/10162_aab2f04d/index.m3u8"
        }
      ]
    },
    {
      "name": "电视剧",
      "cards": [
        {
          "name": "鼓舞粤语版",
          "img": "https://pic1.yzzyimg.com/upload/vod/2022-05-10/16521394781.jpg",
          "id": 191258,
          "countStr": "",
          "url": ""
        },
        {
          "name": "风雨桃花镇",
          "img": "https://pic1.yzzyimg.com/upload/vod/2022-05-07/165189757312.jpg",
          "id": 191320,
          "countStr": "",
          "url": ""
        },
        {
          "name": "太傅和公主的“前世今生”",
          "img": "https://pic1.yzzyimg.com/upload/vod/2022-07-06/202207061657071220.jpg",
          "id": 191049,
          "countStr": "",
          "url": ""
        },
        {
          "name": "大鳄无形",
          "img": "https://pic1.yzzyimg.com/upload/vod/2022-04-14/16499389881.jpg",
          "id": 191530,
          "countStr": "",
          "url": ""
        },
        {
          "name": "欢乐一家亲第六季",
          "img": "https://pic1.yzzyimg.com/upload/vod/2022-05-04/165163931410.jpg",
          "id": 191357,
          "countStr": "",
          "url": ""
        },
        {
          "name": "爱的方式",
          "img": "https://pic1.yzzyimg.com/upload/vod/2022-10-14/16657377511.jpg",
          "id": 190284,
          "countStr": "",
          "url": ""
        },
        {
          "name": "关中秘事",
          "img": "https://pic1.yzzyimg.com/upload/vod/2023-04-23/16822079231.jpg",
          "id": 189112,
          "countStr": "",
          "url": ""
        },
        {
          "name": "医神华佗",
          "img": "https://pic1.yzzyimg.com/upload/vod/2022-08-02/16594336061.jpg",
          "id": 190760,
          "countStr": "",
          "url": ""
        },
        {
          "name": "大唐名捕国语",
          "img": "https://pic1.yzzyimg.com/upload/vod/2022-12-09/16705812071.jpg",
          "id": 189714,
          "countStr": "",
          "url": ""
        },
        {
          "name": "江湖再见",
          "img": "https://pic1.yzzyimg.com/upload/vod/2022-12-02/16699845361.jpg",
          "id": 189791,
          "countStr": "",
          "url": ""
        },
        {
          "name": "真情错爱",
          "img": "https://pic1.yzzyimg.com/upload/vod/2022-11-26/16694768701.jpg",
          "id": 189826,
          "countStr": "",
          "url": ""
        },
        {
          "name": "南拳蔡李佛国语版",
          "img": "https://pic1.yzzyimg.com/upload/vod/2022-11-18/16687481561.jpg",
          "id": 189921,
          "countStr": "",
          "url": ""
        },
        {
          "name": "怒海孤鸿粤语版",
          "img": "https://pic1.yzzyimg.com/upload/vod/2022-11-19/16688453691.jpg",
          "id": 189930,
          "countStr": "",
          "url": ""
        },
        {
          "name": "爱没有错",
          "img": "https://pic1.yzzyimg.com/upload/vod/2022-10-04/16648183971.jpg",
          "id": 190386,
          "countStr": "",
          "url": ""
        },
        {
          "name": "费家有女",
          "img": "https://pic1.yzzyimg.com/upload/vod/2022-10-14/16657377121.jpg",
          "id": 190295,
          "countStr": "",
          "url": ""
        },
        {
          "name": "盏鬼老豆粤语版",
          "img": "https://pic1.yzzyimg.com/upload/vod/2022-11-14/16684299601.jpg",
          "id": 190002,
          "countStr": "",
          "url": ""
        }
      ]
    },
    {
      "name": "动漫",
      "cards": [
        {
          "name": "无敌龙卷风",
          "img": "https://pic1.yzzyimg.com/upload/vod/2022-04-28/16511491389.jpg",
          "id": 193216,
          "countStr": "",
          "url": ""
        },
        {
          "name": "武逆",
          "img": "https://pic1.yzzyimg.com/upload/vod/2022-04-15/202204151650023642.png",
          "id": 193275,
          "countStr": "",
          "url": ""
        },
        {
          "name": "美妙旋律第九季",
          "img": "https://svip.picffzy.com/upload/vod/20230127-1/4f945c36b40d263fa9599745969331a0.jpg",
          "id": 179034,
          "countStr": "",
          "url": ""
        },
        {
          "name": "关于我转生变成史莱姆这档事",
          "img": "https://pic1.yzzyimg.com/upload/vod/2023-01-09/202301091673226070.jpg",
          "id": 192869,
          "countStr": "",
          "url": ""
        },
        {
          "name": "今天开始闪耀登场",
          "img": "https://pic1.yzzyimg.com/upload/vod/2023-03-30/16801432171.jpg",
          "id": 192537,
          "countStr": "",
          "url": ""
        },
        {
          "name": "无职转生Ⅱ～到了异世界就拿出真本事～",
          "img": "https://yc.cdn.media.ulivetv.net/media/img/2023-10-04/9fec9120db53c5264113807aa1976530.jpg",
          "id": 111267,
          "countStr": "更新至1集",
          "url": ""
        },
        {
          "name": "功夫熊猫:神龙骑士第三季",
          "img": "https://svip.picffzy.com/upload/vod/20230907-1/26e2569010a75a12428a32cf418383c6.jpg",
          "id": 177785,
          "countStr": "",
          "url": ""
        },
        {
          "name": "B-PROJECT第三季",
          "img": "https://yc.cdn.media.ulivetv.net/media/img/2023-10-06/57bedfc5b08db02ee7886c5ff4cb1dbb.jpg",
          "id": 125782,
          "countStr": "",
          "url": ""
        },
        {
          "name": "盾之勇者成名录第三季",
          "img": "https://yc.cdn.media.ulivetv.net/media/img/2023-10-06/0954e22f8955ded29b4a3cfa37524b11.jpg",
          "id": 131272,
          "countStr": "",
          "url": ""
        },
        {
          "name": "大雪海的凯纳",
          "img": "https://yc.cdn.media.ulivetv.net/media/img/2023-05-18/e5d2ad9aa81c0929186d8daf001a29db.webp",
          "id": 71755,
          "countStr": "更新至11集",
          "url": ""
        },
        {
          "name": "亡骸游戏Part2",
          "img": "https://yc.cdn.media.ulivetv.net/media/img/2023-10-09/7beb7905947f9c2f370f39d9926d763a.jpg",
          "id": 150003,
          "countStr": "",
          "url": ""
        },
        {
          "name": "川越BoysSing",
          "img": "https://yc.cdn.media.ulivetv.net/media/img/2023-10-09/014ec28eeaf59fea7ec8ae69fa6d46aa.jpg",
          "id": 150265,
          "countStr": "",
          "url": ""
        },
        {
          "name": "猪肝倒是热热再吃啊",
          "img": "https://yc.cdn.media.ulivetv.net/media/img/2023-10-08/b58e7cdc95d051a3461dd702cf814f31.jpg",
          "id": 143279,
          "countStr": "",
          "url": ""
        },
        {
          "name": "超超超超超喜欢你的100个女朋友",
          "img": "https://yc.cdn.media.ulivetv.net/media/img/2023-10-08/bc1117103afa1f091f20558f0de21be3.jpg",
          "id": 143752,
          "countStr": "",
          "url": ""
        },
        {
          "name": "我们的雨色协议",
          "img": "https://yc.cdn.media.ulivetv.net/media/img/2023-10-08/62523ef042f69eb3edb086873d2a4fb4.jpg",
          "id": 143281,
          "countStr": "",
          "url": ""
        },
        {
          "name": "女友成堆第二季",
          "img": "https://yc.cdn.media.ulivetv.net/media/img/2023-10-07/1edcfd2dccd69f53bc9a24dfd4fffd78.jpg",
          "id": 139110,
          "countStr": "",
          "url": ""
        }
      ]
    },
    {
      "name": "综艺",
      "cards": [
        {
          "name": "全能歌手",
          "img": "https://pic1.yzzyimg.com/upload/vod/2023-07-25/202307251690242412.jpg",
          "id": 191614,
          "countStr": "",
          "url": ""
        },
        {
          "name": "童话2023",
          "img": "https://pic1.yzzyimg.com/upload/vod/2023-08-16/16921572761.jpg",
          "id": 191604,
          "countStr": "",
          "url": ""
        },
        {
          "name": "令人心动的offer 第五季",
          "img": "https://pic1.yzzyimg.com/upload/vod/2023-09-25/16956446311.jpg",
          "id": 191605,
          "countStr": "",
          "url": ""
        },
        {
          "name": "星星伴我心",
          "img": "https://svip.picffzy.com/upload/vod/20231004-1/4b07b40591987a81e4fe5970b65a8fd7.jpg",
          "id": 176345,
          "countStr": "",
          "url": ""
        },
        {
          "name": "家务优等生",
          "img": "https://svip.picffzy.com/upload/vod/20230823-1/63d08bfe6baba2c86838aedf55309697.jpg",
          "id": 176437,
          "countStr": "",
          "url": ""
        },
        {
          "name": "妈妈是神队友",
          "img": "https://svip.picffzy.com/upload/vod/20231010-1/5749964ff465f51bbe7d4f7a10510ecb.jpg",
          "id": 176370,
          "countStr": "",
          "url": ""
        },
        {
          "name": "我们的歌第五季",
          "img": "https://yc.cdn.media.ulivetv.net/media/img/2023-10-08/a8927e2553938e74e229bfaccb01a5e8.jpg",
          "id": 143994,
          "countStr": "",
          "url": ""
        },
        {
          "name": "哎呀好身材奔赴季",
          "img": "https://yc.cdn.media.ulivetv.net/media/img/2023-10-07/c0d94dfef14440a53df1c56ef597539f.webp",
          "id": 137293,
          "countStr": "",
          "url": ""
        },
        {
          "name": "中央广播电视总台2023主持人大赛",
          "img": "https://svip.picffzy.com/upload/vod/20231007-1/0a19a71f15327c72a442b0c63fa30c9f.jpg",
          "id": 176405,
          "countStr": "",
          "url": ""
        },
        {
          "name": "少男少女恋爱",
          "img": "https://yc.cdn.media.ulivetv.net/media/img/2023-10-09/db6b678d6d199d624e58cb747e075d4d.jpg",
          "id": 147697,
          "countStr": "",
          "url": ""
        },
        {
          "name": "5Flix",
          "img": "https://svip.picffzy.com/upload/vod/20231009-1/b23f1d2edf7e00355b72a7b6a34fdf08.jpg",
          "id": 176342,
          "countStr": "",
          "url": ""
        },
        {
          "name": "强心脏联盟",
          "img": "https://yc.cdn.media.ulivetv.net/media/img/2023-05-30/66b184b169f689967717b0689ad2c2e8.webp",
          "id": 34093,
          "countStr": "更新至12集",
          "url": ""
        },
        {
          "name": "卡戴珊家族第四季",
          "img": "https://yc.cdn.media.ulivetv.net/media/img/2023-10-04/ed6162683267ef7059a8a266d8b2b9c7.jpg",
          "id": 115562,
          "countStr": "",
          "url": ""
        },
        {
          "name": "2023中秋奇妙游",
          "img": "https://yc.cdn.media.ulivetv.net/media/img/2023-09-29/504757868a7fd67246689c5d9a8fcf7d.webp",
          "id": 110523,
          "countStr": "",
          "url": ""
        },
        {
          "name": "卡戴珊家族第四季",
          "img": "https://yc.cdn.media.ulivetv.net/media/img/2023-10-08/c6a0269e22d3716e7fcffd18f47af8b5.jpg",
          "id": 142038,
          "countStr": "更新至2集",
          "url": ""
        },
        {
          "name": "封神训练营",
          "img": "https://yc.cdn.media.ulivetv.net/media/img/2023-09-28/fcb2e6e03ca6331d196b173186a36eaa.jpg",
          "id": 110513,
          "countStr": "",
          "url": ""
        }
      ]
    },
    {
      "name": "纪录片",
      "cards": [
        {
          "name": "火山挚恋",
          "img": "https://img.kuaikanzy.net/upload/vod/20230311-8/f05cbed7c4e8483a5b86b148c187d880.jpg",
          "id": 110391,
          "countStr": "",
          "url": ""
        },
        {
          "name": "火山挚恋",
          "img": "https://yc.cdn.media.ulivetv.net/media/img/2023-05-19/3e54ba731be4eb56ecb4f4fc89256207.webp",
          "id": 24831,
          "countStr": "共1集",
          "url": ""
        },
        {
          "name": "维拉潘：印度头号通缉犯",
          "img": "https://yc.cdn.media.ulivetv.net/media/img/2023-08-06/c416fd1bf597338f9b9b53061cac3998.webp",
          "id": 82882,
          "countStr": "",
          "url": ""
        },
        {
          "name": "汉斯·季默：好莱坞的反叛者",
          "img": "https://img.kuaikanzy.net/upload/vod/20230327-1/2d42da3c61b521b1edfd7e176b65ebfc.jpg",
          "id": 110415,
          "countStr": "",
          "url": ""
        },
        {
          "name": "史前星球第二季",
          "img": "https://yc.cdn.media.ulivetv.net/media/img/2023-06-08/71d2bc12a984a1e48fee5c88c57adcf0.webp",
          "id": 82229,
          "countStr": "共5集",
          "url": ""
        },
        {
          "name": "失踪调查组：生死未卜第一季",
          "img": "https://img.kuaikanzy.net/upload/vod/20230531-2/168d5a949965b8a05e22c8fe11cb67c1.jpg",
          "id": 110132,
          "countStr": "",
          "url": ""
        },
        {
          "name": "闪闪的儿科医生",
          "img": "https://img.kuaikanzy.net/upload/vod/20230531-2/ea526d2e588f7364ff45c71abe0a1c40.jpg",
          "id": 110119,
          "countStr": "",
          "url": ""
        },
        {
          "name": "超凡动物奇观",
          "img": "https://img.kuaikanzy.net/upload/vod/20230527-1/d2a7761d046383cc26cdb9d582991163.jpg",
          "id": 110386,
          "countStr": "",
          "url": ""
        },
        {
          "name": "超凡动物奇观",
          "img": "https://yc.cdn.media.ulivetv.net/media/img/2023-05-30/e28ea541f94de5147bf7fabb8300681b.webp",
          "id": 34066,
          "countStr": "共6集",
          "url": ""
        },
        {
          "name": "超乎人性",
          "img": "https://img.kuaikanzy.net/upload/vod/20230531-2/66fb89b3db438ade65d9456f007bbf80.jpg",
          "id": 110123,
          "countStr": "",
          "url": ""
        },
        {
          "name": "刘易斯·卡帕尔迪：此刻的我",
          "img": "https://img.kuaikanzy.net/upload/vod/20230531-2/bbd1d6f69c3e5490727082d4cd869898.jpg",
          "id": 110159,
          "countStr": "",
          "url": ""
        },
        {
          "name": "急诊先锋：纽约第一季",
          "img": "https://img.kuaikanzy.net/upload/vod/20230531-2/bd7a56c1c58decebb379d0cf2175a4d6.jpg",
          "id": 110139,
          "countStr": "",
          "url": ""
        },
        {
          "name": "韦科惨案：末日烈火第一季",
          "img": "https://img.kuaikanzy.net/upload/vod/20230327-1/916caa62c580cbc1c12298ad84938dc2.jpg",
          "id": 110331,
          "countStr": "",
          "url": ""
        },
        {
          "name": "与博诺和边缘面对面:大卫·莱特曼回归都柏林",
          "img": "https://img.kuaikanzy.net/upload/vod/20230327-1/a121fa77a375259325e90d1fa2d160ae.jpg",
          "id": 110242,
          "countStr": "",
          "url": ""
        },
        {
          "name": "怪物工厂",
          "img": "https://img.kuaikanzy.net/upload/vod/20230327-1/3dc69fa657e4621226904e3470144fa9.jpg",
          "id": 110249,
          "countStr": "",
          "url": ""
        },
        {
          "name": "全面揭发：印度板球造假丑闻",
          "img": "https://img.kuaikanzy.net/upload/vod/20230327-1/19802f3472b1150561880c6fe5e28ecc.jpg",
          "id": 110235,
          "countStr": "",
          "url": ""
        }
      ]
    }
  ],
  "headers": [
    {
      "id": 97655,
      "label": "",
      "countStr": "2023 / 欧美",
      "focusName": "飙车，但是你来当赛车手！",
      "name": "GT赛车：极速狂飙",
      "posterImg": "https://yc.cdn.media.ulivetv.net/media/other/2023-10-13/ed67f4bc420fc7a928396a0facc3e333.webp",
      "picImg": "https://yc.cdn.media.ulivetv.net/media/img/2023-09-26/091c92c540579b5fecb79542846c1113.webp",
      "startTime": 1697126400,
      "endTime": 1701273600,
      "url": "https://aws.ulivetv.net/v3/api/dianbo/m3u8/649147_kk.m3u8"
    },
    {
      "id": 96948,
      "label": "动作 / 惊悚 / 冒险",
      "countStr": "2023 / 欧美",
      "focusName": "年过六旬的阿汤哥，依旧在挑战玩命极限！",
      "name": "碟中谍7：致命清算（上）",
      "posterImg": "https://yc.cdn.media.ulivetv.net/media/other/2023-10-10/036bd2babb7e6c7b943b59ba9242fbca.webp",
      "picImg": "https://yc.cdn.media.ulivetv.net/media/img/2023-07-12/50cc4c79071254abd01154ae8f082bcc.webp",
      "startTime": 1696867200,
      "endTime": 1701273600,
      "url": ""
    },
    {
      "id": "98636",
      "label": "喜剧 / 古装",
      "countStr": "2023 / 大陆",
      "focusName": "笑裂！“大娘子”嫁女选婿！",
      "name": "兰闺喜事",
      "posterImg": "https://yc.cdn.media.ulivetv.net/media/other/2023-09-27/6f4b3f86f08d2e5a236adbcbe313bf0d.webp",
      "picImg": "https://yc.cdn.media.ulivetv.net/media/img/2023-09-22/f0320e366635529e9ce2bc53059ddb15.webp",
      "startTime": 1696348800,
      "endTime": 1698681600,
      "url": ""
    },
    {
      "id": "98571",
      "label": "剧情",
      "countStr": "2023 / 大陆",
      "focusName": "留给黄景瑜出演的特种兵不多了！",
      "name": "他从火光中走来",
      "posterImg": "https://yc.cdn.media.ulivetv.net/media/other/2023-09-27/71e0c5d08c8ec35222e3a146e16e9dd2.webp",
      "picImg": "https://yc.cdn.media.ulivetv.net/media/img/2023-09-19/6eeadfb1c0daa47d9bdba47c6412e350.webp",
      "startTime": 1695830400,
      "endTime": 1698681600,
      "url": ""
    },
    {
      "id": "97383",
      "label": "动作 / 战争 / 奇幻 / 古装",
      "countStr": "2023 / 大陆",
      "focusName": "费翔率领封神“质子团”燃爆出征！",
      "name": "封神第一部：朝歌风云",
      "posterImg": "https://yc.cdn.media.ulivetv.net/media/other/2023-09-22/febe309e76d372a534e48b1ada77955a.webp",
      "picImg": "https://yc.cdn.media.ulivetv.net/media/img/2023-07-27/e25e3f6883acb2cd594e1cfef5b9c30a.webp",
      "startTime": 1695312000,
      "endTime": 1698681600,
      "url": "https://aws.ulivetv.net/v3/api/dianbo/m3u8/498736_kk.m3u8"
    },
    {
      "id": "98245",
      "label": "剧情 / 爱情 / 悬疑 / 冒险",
      "countStr": "2023 / 大陆",
      "focusName": "白宇干练，倪妮飒爽，主打演技对飚的异域冒险！",
      "name": "西出玉门",
      "posterImg": "https://d3ifppxyz9sa2s.cloudfront.net/media/other/2023-09-12/0aab2c2548f8940def1015e99033c9d0.webp",
      "picImg": "https://yc.cdn.media.ulivetv.net/media/img/2023-05-18/1bc7d4db4e49c03836264e0b161fd8e7.webp",
      "startTime": 1694448000,
      "endTime": 1698681600,
      "url": ""
    }
  ]
}